stargql/__init__.py
stargql/__version__.py
stargql/applications.py
stargql/subscription.py
starlette_graphql-0.1.5.dist-info/LICENSE
starlette_graphql-0.1.5.dist-info/WHEEL
starlette_graphql-0.1.5.dist-info/METADATA
starlette_graphql-0.1.5.dist-info/RECORD
