Metadata-Version: 2.1
Name: starlette-graphql
Version: 0.1.5
Summary: The starlette GraphQL implement, which  support query, mutate and subscription.
Home-page: https://github.com/syfun/starlette-graphql
License: MIT
Author: syfun
Author-email: sunyu418@gmail.com
Requires-Python: >3.7
Classifier: License :: OSI Approved :: MIT License
Classifier: Programming Language :: Python :: 3
Classifier: Programming Language :: Python :: 3.8
Requires-Dist: python-gql (>=0.1)
Requires-Dist: starlette (>0.13)
